aiida/__init__.py
aiida/__main__.py
aiida/py.typed
aiida/brokers/__init__.py
aiida/brokers/broker.py
aiida/brokers/rabbitmq/__init__.py
aiida/brokers/rabbitmq/broker.py
aiida/brokers/rabbitmq/client.py
aiida/brokers/rabbitmq/defaults.py
aiida/brokers/rabbitmq/utils.py
aiida/calculations/__init__.py
aiida/calculations/stash.py
aiida/calculations/templatereplacer.py
aiida/calculations/transfer.py
aiida/calculations/arithmetic/__init__.py
aiida/calculations/arithmetic/add.py
aiida/calculations/diff_tutorial/calculations.py
aiida/calculations/importers/__init__.py
aiida/calculations/importers/arithmetic/__init__.py
aiida/calculations/importers/arithmetic/add.py
aiida/calculations/monitors/__init__.py
aiida/calculations/monitors/base.py
aiida/cmdline/__init__.py
aiida/cmdline/commands/__init__.py
aiida/cmdline/commands/cmd_archive.py
aiida/cmdline/commands/cmd_calcjob.py
aiida/cmdline/commands/cmd_code.py
aiida/cmdline/commands/cmd_computer.py
aiida/cmdline/commands/cmd_config.py
aiida/cmdline/commands/cmd_daemon.py
aiida/cmdline/commands/cmd_devel.py
aiida/cmdline/commands/cmd_group.py
aiida/cmdline/commands/cmd_help.py
aiida/cmdline/commands/cmd_node.py
aiida/cmdline/commands/cmd_plugin.py
aiida/cmdline/commands/cmd_presto.py
aiida/cmdline/commands/cmd_process.py
aiida/cmdline/commands/cmd_profile.py
aiida/cmdline/commands/cmd_rabbitmq.py
aiida/cmdline/commands/cmd_restapi.py
aiida/cmdline/commands/cmd_run.py
aiida/cmdline/commands/cmd_setup.py
aiida/cmdline/commands/cmd_shell.py
aiida/cmdline/commands/cmd_status.py
aiida/cmdline/commands/cmd_storage.py
aiida/cmdline/commands/cmd_user.py
aiida/cmdline/commands/cmd_verdi.py
aiida/cmdline/commands/cmd_data/__init__.py
aiida/cmdline/commands/cmd_data/cmd_array.py
aiida/cmdline/commands/cmd_data/cmd_bands.py
aiida/cmdline/commands/cmd_data/cmd_cif.py
aiida/cmdline/commands/cmd_data/cmd_dict.py
aiida/cmdline/commands/cmd_data/cmd_export.py
aiida/cmdline/commands/cmd_data/cmd_list.py
aiida_core-2.7.3.dist-info/entry_points.txt
aiida_core-2.7.3.dist-info/licenses/LICENSE.txt
aiida_core-2.7.3.dist-info/WHEEL
aiida_core-2.7.3.dist-info/METADATA
aiida_core-2.7.3.dist-info/RECORD
