Metadata-Version: 2.4
Name: aiida-core
Version: 2.7.3
Summary: AiiDA is a workflow manager for computational science with a strong focus on provenance, performance and extensibility.
Keywords: aiida,workflows
Author-email: The AiiDA team <developers@aiida.net>
Requires-Python: >=3.9
Classifier: Development Status :: 5 - Production/Stable
Classifier: Framework :: AiiDA
Classifier: License :: OSI Approved :: MIT License
Classifier: Operating System :: POSIX :: Linux
Classifier: Operating System :: MacOS :: MacOS X
Classifier: Programming Language :: Python
Classifier: Programming Language :: Python :: 3.9
Classifier: Programming Language :: Python :: 3.10
Classifier: Programming Language :: Python :: 3.11
Classifier: Programming Language :: Python :: 3.12
Classifier: Programming Language :: Python :: 3.13
Classifier: Topic :: Scientific/Engineering
License-File: LICENSE.txt
Requires-Dist: alembic~=1.2
Requires-Dist: archive-path~=0.4.2
Requires-Dist: asyncssh~=2.19.0
Requires-Dist: circus~=0.19.0
Requires-Dist: click-spinner~=0.1.8
Requires-Dist: click~=8.1.0
Requires-Dist: disk-objectstore~=1.3.0
Requires-Dist: docstring-parser
Requires-Dist: get-annotations~=0.1;python_version<"3.10"
Requires-Dist: graphviz~=0.19
Requires-Dist: plumpy~=0.25.0
Requires-Dist: ipython>=7
Requires-Dist: jedi<0.19
Requires-Dist: jinja2~=3.0
Requires-Dist: kiwipy[rmq]~=0.8.4
Requires-Dist: importlib-metadata~=6.0
Requires-Dist: numpy~=1.21
Requires-Dist: paramiko~=3.0
Requires-Dist: pgsu~=0.3.0
Requires-Dist: psutil~=5.6
Requires-Dist: psycopg[binary]~=3.0
Requires-Dist: pydantic~=2.4
Requires-Dist: pytz~=2021.1
Requires-Dist: pyyaml~=6.0
Requires-Dist: requests~=2.0
Requires-Dist: sqlalchemy~=2.0
Requires-Dist: tabulate>=0.8.0,<0.10.0
Requires-Dist: tqdm~=4.45
Requires-Dist: typing-extensions~=4.0;python_version<"3.10"
Requires-Dist: upf_to_json~=0.9.2
Requires-Dist: wrapt~=1.11
Requires-Dist: chardet~=5.2.0;platform_system=="Windows"
Requires-Dist: PyCifRW~=4.4 ; extra == "atomic-tools"
Requires-Dist: ase~=3.18 ; extra == "atomic-tools"
Requires-Dist: matplotlib~=3.3,>=3.3.4 ; extra == "atomic-tools"
Requires-Dist: pymatgen>=2022.1.20 ; extra == "atomic-tools"
Requires-Dist: pymysql~=0.9.3 ; extra == "atomic-tools"
Requires-Dist: seekpath~=1.9,>=1.9.3 ; extra == "atomic-tools"
Requires-Dist: spglib>=1.14,<3.0 ; extra == "atomic-tools"
Requires-Dist: bpython~=0.18.0 ; extra == "bpython"
Requires-Dist: pydata-sphinx-theme~=0.15.1 ; extra == "docs"
Requires-Dist: sphinx~=7.2.0 ; extra == "docs"
Requires-Dist: sphinx-copybutton~=0.5.0 ; extra == "docs"
Requires-Dist: sphinx-design~=0.5.0 ; extra == "docs"
Requires-Dist: sphinx-notfound-page~=1.0 ; extra == "docs"
Requires-Dist: sphinxext-rediraffe~=0.2.4 ; extra == "docs"
Requires-Dist: sphinx-sqlalchemy~=0.2.0 ; extra == "docs"
Requires-Dist: sphinx-intl~=2.1.0 ; extra == "docs"
Requires-Dist: myst-nb~=1.0.0 ; extra == "docs"
Requires-Dist: jupyter-client~=8.0 ; extra == "notebook"
Requires-Dist: jupyter~=1.0 ; extra == "notebook"
Requires-Dist: notebook~=6.1,>=6.1.5 ; extra == "notebook"
Requires-Dist: aiida-core[atomic-tools, rest, tests, tui] ; extra == "pre-commit"
Requires-Dist: mypy~=1.13.0 ; extra == "pre-commit"
Requires-Dist: packaging~=23.0 ; extra == "pre-commit"
Requires-Dist: pre-commit~=3.5 ; extra == "pre-commit"
Requires-Dist: sqlalchemy[mypy]~=2.0 ; extra == "pre-commit"
Requires-Dist: tomli ; extra == "pre-commit"
Requires-Dist: types-PyYAML ; extra == "pre-commit"
Requires-Dist: flask-cors~=3.0 ; extra == "rest"
Requires-Dist: flask-restful~=0.3.7 ; extra == "rest"
Requires-Dist: flask~=2.2 ; extra == "rest"
Requires-Dist: pyparsing~=3.0 ; extra == "rest"
Requires-Dist: python-memcached~=1.59 ; extra == "rest"
Requires-Dist: seekpath~=1.9,>=1.9.3 ; extra == "rest"
Requires-Dist: gssapi~=1.6 ; extra == "ssh-kerberos"
Requires-Dist: pyasn1~=0.4.8 ; extra == "ssh-kerberos"
Requires-Dist: aiida-export-migration-tests==0.9.0 ; extra == "tests"
Requires-Dist: pg8000~=1.13 ; extra == "tests"
Requires-Dist: pgtest~=1.3,>=1.3.1 ; extra == "tests"
Requires-Dist: pytest~=7.0 ; extra == "tests"
Requires-Dist: pytest-asyncio~=0.12,<0.17 ; extra == "tests"
Requires-Dist: pytest-timeout~=2.0 ; extra == "tests"
Requires-Dist: pytest-cov~=4.1 ; extra == "tests"
Requires-Dist: pytest-rerunfailures~=12.0 ; extra == "tests"
Requires-Dist: pytest-benchmark~=4.0 ; extra == "tests"
Requires-Dist: pytest-regressions~=2.2 ; extra == "tests"
Requires-Dist: pytest-xdist~=3.6 ; extra == "tests"
Requires-Dist: pympler~=1.0 ; extra == "tests"
Requires-Dist: coverage~=7.0 ; extra == "tests"
Requires-Dist: sphinx~=7.2.0 ; extra == "tests"
Requires-Dist: docutils~=0.20 ; extra == "tests"
Requires-Dist: trogon ; extra == "tui"
Project-URL: Changelog, https://github.com/aiidateam/aiida-core/blob/main/CHANGELOG.md
Project-URL: Documentation, https://aiida.readthedocs.io
Project-URL: Home, http://www.aiida.net/
Project-URL: Source, https://github.com/aiidateam/aiida-core
Provides-Extra: atomic-tools
Provides-Extra: bpython
Provides-Extra: docs
Provides-Extra: notebook
Provides-Extra: pre-commit
Provides-Extra: rest
Provides-Extra: ssh-kerberos
Provides-Extra: tests
Provides-Extra: tui
